nbstrip.py
nbstrip-0.1.1.dist-info/LICENSE
nbstrip-0.1.1.dist-info/METADATA
nbstrip-0.1.1.dist-info/WHEEL
nbstrip-0.1.1.dist-info/entry_points.txt
nbstrip-0.1.1.dist-info/top_level.txt
nbstrip-0.1.1.dist-info/RECORD
